{
  "彩种": "排列三",
  "数据截至期号": 26129,
  "预测期号": 26130,
  "评分时间": "2026-05-20 18:38:32",
  "top_k": 30,
  "风险提示": "⚠️ 彩票开奖具有高度随机性，本评分仅基于历史统计和理论分布，不代表未来开奖结果。请理性看待，量力而行。",
  "摘要": {
    "总分最高": 67,
    "总分最低": 61,
    "平均分": 63.6,
    "跨度分布": {
      "3": 6,
      "4": 4,
      "5": 8,
      "7": 8,
      "8": 4
    },
    "组选数量": 30,
    "形态分布": {
      "组六": 23,
      "组三": 7,
      "豹子": 0
    },
    "高分阈值": 60,
    "高分候选数": 42,
    "候选总数": 985,
    "P90分数线": 55,
    "P90候选数": 118,
    "P95分数线": 59,
    "P95候选数": 50,
    "Top10号码": [
      "168",
      "189",
      "126",
      "235",
      "129",
      "138",
      "188",
      "225",
      "366",
      "118"
    ],
    "Top30号码": [
      "168",
      "189",
      "126",
      "235",
      "129",
      "138",
      "188",
      "225",
      "366",
      "118",
      "156",
      "169",
      "356",
      "125",
      "255",
      "267",
      "279",
      "336",
      "358",
      "368",
      "378",
      "116",
      "135",
      "136",
      "256",
      "259",
      "269",
      "367",
      "018",
      "158"
    ]
  },
  "过滤说明": {
    "排除近N期": 5,
    "是否排除豹子": true,
    "排除模式": "direct"
  },
  "生成信息": {
    "命令": "python scripts/scoring_engine.py --lottery pls --top-k 30 --exclude-recent 5 --exclude-mode direct",
    "权重文件": "rules\\scoring_weights_diversity.yaml",
    "统计缓存": "data\\cache\\pls_stats_latest.json",
    "数据文件": "data\\processed\\pls_feat.csv",
    "代码版本": "2244ede"
  },
  "权重": {
    "和值": 15,
    "跨度": 12,
    "形态": 10,
    "奇偶": 8,
    "大小": 8,
    "012路": 7,
    "冷热": 8,
    "遗漏": 7,
    "组三/六偏向": 8,
    "多样性": 20
  },
  "参数": {
    "cold_threshold": 6,
    "hot_threshold": 3,
    "group_penalty": 10,
    "span_spread": 15,
    "overheat_high": 0.6,
    "overheat_medium": 0.8
  },
  "推荐": [
    {
      "排名": 1,
      "号码": "168",
      "group_number": "168",
      "和值": 15,
      "跨度": 7,
      "形态": "组六",
      "总分": 67,
      "推荐理由": "和值=11 跨度=9 形态=9",
      "展示理由": "第1名 | 168 (组六) | 总分67 | 和值=11 跨度=9 形态=9",
      "一句话说明": "和值15、跨度7，形态为组六，和值 跨度 得分较高。",
      "评分明细": {
        "和值": [
          11,
          "和值=15"
        ],
        "跨度": [
          9,
          "跨度=7"
        ],
        "形态": [
          9,
          "形态=组六"
        ],
        "奇偶": [
          8,
          "奇=1"
        ],
        "大小": [
          8,
          "大=2"
        ],
        "012路": [
          7,
          "0路=1,1路=1,2路=1"
        ],
        "冷热": [
          8,
          "冷号=0"
        ],
        "遗漏": [
          7,
          "均遗=2.4"
        ],
        "多样性": [
          0,
          "组选唯一"
        ]
      }
    },
    {
      "排名": 2,
      "号码": "189",
      "group_number": "189",
      "和值": 18,
      "跨度": 8,
      "形态": "组六",
      "总分": 67,
      "推荐理由": "和值=11 形态=9 奇偶=8",
      "展示理由": "第2名 | 189 (组六) | 总分67 | 和值=11 形态=9 奇偶=8",
      "一句话说明": "和值18、跨度8，形态为组六，和值 形态 得分较高。",
      "评分明细": {
        "和值": [
          11,
          "和值=18"
        ],
        "跨度": [
          6,
          "跨度=8"
        ],
        "形态": [
          9,
          "形态=组六"
        ],
        "奇偶": [
          8,
          "奇=2"
        ],
        "大小": [
          8,
          "大=2"
        ],
        "012路": [
          7,
          "0路=1,1路=1,2路=1"
        ],
        "冷热": [
          8,
          "冷号=0"
        ],
        "遗漏": [
          5,
          "均遗=2.4"
        ],
        "多样性": [
          5,
          "跨度8加5"
        ]
      }
    },
    {
      "排名": 3,
      "号码": "126",
      "group_number": "126",
      "和值": 9,
      "跨度": 5,
      "形态": "组六",
      "总分": 66,
      "推荐理由": "和值=11 形态=9 跨度=8",
      "展示理由": "第3名 | 126 (组六) | 总分66 | 和值=11 形态=9 跨度=8",
      "一句话说明": "和值9、跨度5，形态为组六，和值 形态 得分较高。",
      "评分明细": {
        "和值": [
          11,
          "和值=9"
        ],
        "跨度": [
          8,
          "跨度=5"
        ],
        "形态": [
          9,
          "形态=组六"
        ],
        "奇偶": [
          8,
          "奇=1"
        ],
        "大小": [
          8,
          "大=1"
        ],
        "012路": [
          7,
          "0路=1,1路=1,2路=1"
        ],
        "冷热": [
          8,
          "冷号=0"
        ],
        "遗漏": [
          7,
          "均遗=2.4"
        ],
        "多样性": [
          0,
          "组选唯一"
        ]
      }
    },
    {
      "排名": 4,
      "号码": "235",
      "group_number": "235",
      "和值": 10,
      "跨度": 3,
      "形态": "组六",
      "总分": 66,
      "推荐理由": "和值=11 形态=9 奇偶=8",
      "展示理由": "第4名 | 235 (组六) | 总分66 | 和值=11 形态=9 奇偶=8",
      "一句话说明": "和值10、跨度3，形态为组六，和值 形态 得分较高。",
      "评分明细": {
        "和值": [
          11,
          "和值=10"
        ],
        "跨度": [
          7,
          "跨度=3"
        ],
        "形态": [
          9,
          "形态=组六"
        ],
        "奇偶": [
          8,
          "奇=2"
        ],
        "大小": [
          8,
          "大=1"
        ],
        "012路": [
          3,
          "0路=1,1路=0,2路=2"
        ],
        "冷热": [
          8,
          "冷号=0"
        ],
        "遗漏": [
          7,
          "均遗=2.4"
        ],
        "多样性": [
          5,
          "跨度3加5"
        ]
      }
    },
    {
      "排名": 5,
      "号码": "129",
      "group_number": "129",
      "和值": 12,
      "跨度": 8,
      "形态": "组六",
      "总分": 65,
      "推荐理由": "和值=9 形态=9 奇偶=8",
      "展示理由": "第5名 | 129 (组六) | 总分65 | 和值=9 形态=9 奇偶=8",
      "一句话说明": "和值12、跨度8，形态为组六，和值 形态 得分较高。",
      "评分明细": {
        "和值": [
          9,
          "和值=12"
        ],
        "跨度": [
          6,
          "跨度=8"
        ],
        "形态": [
          9,
          "形态=组六"
        ],
        "奇偶": [
          8,
          "奇=2"
        ],
        "大小": [
          8,
          "大=1"
        ],
        "012路": [
          7,
          "0路=1,1路=1,2路=1"
        ],
        "冷热": [
          8,
          "冷号=0"
        ],
        "遗漏": [
          5,
          "均遗=2.4"
        ],
        "多样性": [
          5,
          "跨度8加5"
        ]
      }
    },
    {
      "排名": 6,
      "号码": "138",
      "group_number": "138",
      "和值": 12,
      "跨度": 7,
      "形态": "组六",
      "总分": 65,
      "推荐理由": "和值=9 跨度=9 形态=9",
      "展示理由": "第6名 | 138 (组六) | 总分65 | 和值=9 跨度=9 形态=9",
      "一句话说明": "和值12、跨度7，形态为组六，和值 跨度 得分较高。",
      "评分明细": {
        "和值": [
          9,
          "和值=12"
        ],
        "跨度": [
          9,
          "跨度=7"
        ],
        "形态": [
          9,
          "形态=组六"
        ],
        "奇偶": [
          8,
          "奇=2"
        ],
        "大小": [
          8,
          "大=1"
        ],
        "012路": [
          7,
          "0路=1,1路=1,2路=1"
        ],
        "冷热": [
          8,
          "冷号=0"
        ],
        "遗漏": [
          7,
          "均遗=2.4"
        ],
        "多样性": [
          0,
          "组选唯一"
        ]
      }
    },
    {
      "排名": 7,
      "号码": "188",
      "group_number": "188",
      "和值": 17,
      "跨度": 7,
      "形态": "组三",
      "总分": 65,
      "推荐理由": "和值=12 形态=10 跨度=9",
      "展示理由": "第7名 | 188 (组三) | 总分65 | 和值=12 形态=10 跨度=9",
      "一句话说明": "和值17、跨度7，形态为组三，和值 形态 得分较高。",
      "评分明细": {
        "和值": [
          12,
          "和值=17"
        ],
        "跨度": [
          9,
          "跨度=7"
        ],
        "形态": [
          10,
          "形态=组三"
        ],
        "奇偶": [
          8,
          "奇=1"
        ],
        "大小": [
          8,
          "大=2"
        ],
        "012路": [
          3,
          "0路=0,1路=1,2路=2"
        ],
        "冷热": [
          8,
          "冷号=0"
        ],
        "遗漏": [
          7,
          "均遗=2.4"
        ],
        "多样性": [
          0,
          "组选唯一"
        ]
      }
    },
    {
      "排名": 8,
      "号码": "225",
      "group_number": "225",
      "和值": 9,
      "跨度": 3,
      "形态": "组三",
      "总分": 65,
      "推荐理由": "和值=11 形态=10 奇偶=8",
      "展示理由": "第8名 | 225 (组三) | 总分65 | 和值=11 形态=10 奇偶=8",
      "一句话说明": "和值9、跨度3，形态为组三，和值 形态 得分较高。",
      "评分明细": {
        "和值": [
          11,
          "和值=9"
        ],
        "跨度": [
          7,
          "跨度=3"
        ],
        "形态": [
          10,
          "形态=组三"
        ],
        "奇偶": [
          8,
          "奇=1"
        ],
        "大小": [
          8,
          "大=1"
        ],
        "012路": [
          1,
          "0路=0,1路=0,2路=3"
        ],
        "冷热": [
          8,
          "冷号=0"
        ],
        "遗漏": [
          7,
          "均遗=2.4"
        ],
        "多样性": [
          5,
          "跨度3加5"
        ]
      }
    },
    {
      "排名": 9,
      "号码": "366",
      "group_number": "366",
      "和值": 15,
      "跨度": 3,
      "形态": "组三",
      "总分": 65,
      "推荐理由": "和值=11 形态=10 奇偶=8",
      "展示理由": "第9名 | 366 (组三) | 总分65 | 和值=11 形态=10 奇偶=8",
      "一句话说明": "和值15、跨度3，形态为组三，和值 形态 得分较高。",
      "评分明细": {
        "和值": [
          11,
          "和值=15"
        ],
        "跨度": [
          7,
          "跨度=3"
        ],
        "形态": [
          10,
          "形态=组三"
        ],
        "奇偶": [
          8,
          "奇=1"
        ],
        "大小": [
          8,
          "大=2"
        ],
        "012路": [
          1,
          "0路=3,1路=0,2路=0"
        ],
        "冷热": [
          8,
          "冷号=0"
        ],
        "遗漏": [
          7,
          "均遗=2.4"
        ],
        "多样性": [
          5,
          "跨度3加5"
        ]
      }
    },
    {
      "排名": 10,
      "号码": "118",
      "group_number": "118",
      "和值": 10,
      "跨度": 7,
      "形态": "组三",
      "总分": 64,
      "推荐理由": "和值=11 形态=10 跨度=9",
      "展示理由": "第10名 | 118 (组三) | 总分64 | 和值=11 形态=10 跨度=9",
      "一句话说明": "和值10、跨度7，形态为组三，和值 形态 得分较高。",
      "评分明细": {
        "和值": [
          11,
          "和值=10"
        ],
        "跨度": [
          9,
          "跨度=7"
        ],
        "形态": [
          10,
          "形态=组三"
        ],
        "奇偶": [
          8,
          "奇=2"
        ],
        "大小": [
          8,
          "大=1"
        ],
        "012路": [
          3,
          "0路=0,1路=2,2路=1"
        ],
        "冷热": [
          8,
          "冷号=0"
        ],
        "遗漏": [
          7,
          "均遗=2.4"
        ],
        "多样性": [
          0,
          "组选唯一"
        ]
      }
    },
    {
      "排名": 11,
      "号码": "156",
      "group_number": "156",
      "和值": 12,
      "跨度": 5,
      "形态": "组六",
      "总分": 64,
      "推荐理由": "和值=9 形态=9 跨度=8",
      "展示理由": "第11名 | 156 (组六) | 总分64 | 和值=9 形态=9 跨度=8",
      "一句话说明": "和值12、跨度5，形态为组六，和值 形态 得分较高。",
      "评分明细": {
        "和值": [
          9,
          "和值=12"
        ],
        "跨度": [
          8,
          "跨度=5"
        ],
        "形态": [
          9,
          "形态=组六"
        ],
        "奇偶": [
          8,
          "奇=2"
        ],
        "大小": [
          8,
          "大=2"
        ],
        "012路": [
          7,
          "0路=1,1路=1,2路=1"
        ],
        "冷热": [
          8,
          "冷号=0"
        ],
        "遗漏": [
          7,
          "均遗=2.4"
        ],
        "多样性": [
          0,
          "组选唯一"
        ]
      }
    },
    {
      "排名": 12,
      "号码": "169",
      "group_number": "169",
      "和值": 16,
      "跨度": 8,
      "形态": "组六",
      "总分": 64,
      "推荐理由": "和值=12 形态=9 奇偶=8",
      "展示理由": "第12名 | 169 (组六) | 总分64 | 和值=12 形态=9 奇偶=8",
      "一句话说明": "和值16、跨度8，形态为组六，和值 形态 得分较高。",
      "评分明细": {
        "和值": [
          12,
          "和值=16"
        ],
        "跨度": [
          6,
          "跨度=8"
        ],
        "形态": [
          9,
          "形态=组六"
        ],
        "奇偶": [
          8,
          "奇=2"
        ],
        "大小": [
          8,
          "大=2"
        ],
        "012路": [
          3,
          "0路=2,1路=1,2路=0"
        ],
        "冷热": [
          8,
          "冷号=0"
        ],
        "遗漏": [
          5,
          "均遗=2.4"
        ],
        "多样性": [
          5,
          "跨度8加5"
        ]
      }
    },
    {
      "排名": 13,
      "号码": "356",
      "group_number": "356",
      "和值": 14,
      "跨度": 3,
      "形态": "组六",
      "总分": 64,
      "推荐理由": "和值=9 形态=9 奇偶=8",
      "展示理由": "第13名 | 356 (组六) | 总分64 | 和值=9 形态=9 奇偶=8",
      "一句话说明": "和值14、跨度3，形态为组六，和值 形态 得分较高。",
      "评分明细": {
        "和值": [
          9,
          "和值=14"
        ],
        "跨度": [
          7,
          "跨度=3"
        ],
        "形态": [
          9,
          "形态=组六"
        ],
        "奇偶": [
          8,
          "奇=2"
        ],
        "大小": [
          8,
          "大=2"
        ],
        "012路": [
          3,
          "0路=2,1路=0,2路=1"
        ],
        "冷热": [
          8,
          "冷号=0"
        ],
        "遗漏": [
          7,
          "均遗=2.4"
        ],
        "多样性": [
          5,
          "跨度3加5"
        ]
      }
    },
    {
      "排名": 14,
      "号码": "125",
      "group_number": "125",
      "和值": 8,
      "跨度": 4,
      "形态": "组六",
      "总分": 63,
      "推荐理由": "和值=10 跨度=10 形态=9",
      "展示理由": "第14名 | 125 (组六) | 总分63 | 和值=10 跨度=10 形态=9",
      "一句话说明": "和值8、跨度4，形态为组六，和值 跨度 得分较高。",
      "评分明细": {
        "和值": [
          10,
          "和值=8"
        ],
        "跨度": [
          10,
          "跨度=4"
        ],
        "形态": [
          9,
          "形态=组六"
        ],
        "奇偶": [
          8,
          "奇=2"
        ],
        "大小": [
          8,
          "大=1"
        ],
        "012路": [
          3,
          "0路=0,1路=1,2路=2"
        ],
        "冷热": [
          8,
          "冷号=0"
        ],
        "遗漏": [
          7,
          "均遗=2.4"
        ],
        "多样性": [
          0,
          "组选唯一"
        ]
      }
    },
    {
      "排名": 15,
      "号码": "255",
      "group_number": "255",
      "和值": 12,
      "跨度": 3,
      "形态": "组三",
      "总分": 63,
      "推荐理由": "形态=10 和值=9 奇偶=8",
      "展示理由": "第15名 | 255 (组三) | 总分63 | 形态=10 和值=9 奇偶=8",
      "一句话说明": "和值12、跨度3，形态为组三，形态 和值 得分较高。",
      "评分明细": {
        "和值": [
          9,
          "和值=12"
        ],
        "跨度": [
          7,
          "跨度=3"
        ],
        "形态": [
          10,
          "形态=组三"
        ],
        "奇偶": [
          8,
          "奇=2"
        ],
        "大小": [
          8,
          "大=2"
        ],
        "012路": [
          1,
          "0路=0,1路=0,2路=3"
        ],
        "冷热": [
          8,
          "冷号=0"
        ],
        "遗漏": [
          7,
          "均遗=2.4"
        ],
        "多样性": [
          5,
          "跨度3加5"
        ]
      }
    },
    {
      "排名": 16,
      "号码": "267",
      "group_number": "267",
      "和值": 15,
      "跨度": 5,
      "形态": "组六",
      "总分": 63,
      "推荐理由": "和值=11 形态=9 跨度=8",
      "展示理由": "第16名 | 267 (组六) | 总分63 | 和值=11 形态=9 跨度=8",
      "一句话说明": "和值15、跨度5，形态为组六，和值 形态 得分较高。",
      "评分明细": {
        "和值": [
          11,
          "和值=15"
        ],
        "跨度": [
          8,
          "跨度=5"
        ],
        "形态": [
          9,
          "形态=组六"
        ],
        "奇偶": [
          8,
          "奇=1"
        ],
        "大小": [
          8,
          "大=2"
        ],
        "012路": [
          7,
          "0路=1,1路=1,2路=1"
        ],
        "冷热": [
          8,
          "冷号=0"
        ],
        "遗漏": [
          4,
          "均遗=2.4"
        ],
        "多样性": [
          0,
          "组选唯一"
        ]
      }
    },
    {
      "排名": 17,
      "号码": "279",
      "group_number": "279",
      "和值": 18,
      "跨度": 7,
      "形态": "组六",
      "总分": 63,
      "推荐理由": "和值=11 跨度=9 形态=9",
      "展示理由": "第17名 | 279 (组六) | 总分63 | 和值=11 跨度=9 形态=9",
      "一句话说明": "和值18、跨度7，形态为组六，和值 跨度 得分较高。",
      "评分明细": {
        "和值": [
          11,
          "和值=18"
        ],
        "跨度": [
          9,
          "跨度=7"
        ],
        "形态": [
          9,
          "形态=组六"
        ],
        "奇偶": [
          8,
          "奇=2"
        ],
        "大小": [
          8,
          "大=2"
        ],
        "012路": [
          7,
          "0路=1,1路=1,2路=1"
        ],
        "冷热": [
          8,
          "冷号=0"
        ],
        "遗漏": [
          3,
          "均遗=2.4"
        ],
        "多样性": [
          0,
          "组选唯一"
        ]
      }
    },
    {
      "排名": 18,
      "号码": "336",
      "group_number": "336",
      "和值": 12,
      "跨度": 3,
      "形态": "组三",
      "总分": 63,
      "推荐理由": "形态=10 和值=9 奇偶=8",
      "展示理由": "第18名 | 336 (组三) | 总分63 | 形态=10 和值=9 奇偶=8",
      "一句话说明": "和值12、跨度3，形态为组三，形态 和值 得分较高。",
      "评分明细": {
        "和值": [
          9,
          "和值=12"
        ],
        "跨度": [
          7,
          "跨度=3"
        ],
        "形态": [
          10,
          "形态=组三"
        ],
        "奇偶": [
          8,
          "奇=2"
        ],
        "大小": [
          8,
          "大=1"
        ],
        "012路": [
          1,
          "0路=3,1路=0,2路=0"
        ],
        "冷热": [
          8,
          "冷号=0"
        ],
        "遗漏": [
          7,
          "均遗=2.4"
        ],
        "多样性": [
          5,
          "跨度3加5"
        ]
      }
    },
    {
      "排名": 19,
      "号码": "358",
      "group_number": "358",
      "和值": 16,
      "跨度": 5,
      "形态": "组六",
      "总分": 63,
      "推荐理由": "和值=12 形态=9 跨度=8",
      "展示理由": "第19名 | 358 (组六) | 总分63 | 和值=12 形态=9 跨度=8",
      "一句话说明": "和值16、跨度5，形态为组六，和值 形态 得分较高。",
      "评分明细": {
        "和值": [
          12,
          "和值=16"
        ],
        "跨度": [
          8,
          "跨度=5"
        ],
        "形态": [
          9,
          "形态=组六"
        ],
        "奇偶": [
          8,
          "奇=2"
        ],
        "大小": [
          8,
          "大=2"
        ],
        "012路": [
          3,
          "0路=1,1路=0,2路=2"
        ],
        "冷热": [
          8,
          "冷号=0"
        ],
        "遗漏": [
          7,
          "均遗=2.4"
        ],
        "多样性": [
          0,
          "组选唯一"
        ]
      }
    },
    {
      "排名": 20,
      "号码": "368",
      "group_number": "368",
      "和值": 17,
      "跨度": 5,
      "形态": "组六",
      "总分": 63,
      "推荐理由": "和值=12 形态=9 跨度=8",
      "展示理由": "第20名 | 368 (组六) | 总分63 | 和值=12 形态=9 跨度=8",
      "一句话说明": "和值17、跨度5，形态为组六，和值 形态 得分较高。",
      "评分明细": {
        "和值": [
          12,
          "和值=17"
        ],
        "跨度": [
          8,
          "跨度=5"
        ],
        "形态": [
          9,
          "形态=组六"
        ],
        "奇偶": [
          8,
          "奇=1"
        ],
        "大小": [
          8,
          "大=2"
        ],
        "012路": [
          3,
          "0路=2,1路=0,2路=1"
        ],
        "冷热": [
          8,
          "冷号=0"
        ],
        "遗漏": [
          7,
          "均遗=2.4"
        ],
        "多样性": [
          0,
          "组选唯一"
        ]
      }
    },
    {
      "排名": 21,
      "号码": "378",
      "group_number": "378",
      "和值": 18,
      "跨度": 5,
      "形态": "组六",
      "总分": 63,
      "推荐理由": "和值=11 形态=9 跨度=8",
      "展示理由": "第21名 | 378 (组六) | 总分63 | 和值=11 形态=9 跨度=8",
      "一句话说明": "和值18、跨度5，形态为组六，和值 形态 得分较高。",
      "评分明细": {
        "和值": [
          11,
          "和值=18"
        ],
        "跨度": [
          8,
          "跨度=5"
        ],
        "形态": [
          9,
          "形态=组六"
        ],
        "奇偶": [
          8,
          "奇=2"
        ],
        "大小": [
          8,
          "大=2"
        ],
        "012路": [
          7,
          "0路=1,1路=1,2路=1"
        ],
        "冷热": [
          8,
          "冷号=0"
        ],
        "遗漏": [
          4,
          "均遗=2.4"
        ],
        "多样性": [
          0,
          "组选唯一"
        ]
      }
    },
    {
      "排名": 22,
      "号码": "116",
      "group_number": "116",
      "和值": 8,
      "跨度": 5,
      "形态": "组三",
      "总分": 62,
      "推荐理由": "和值=10 形态=10 跨度=8",
      "展示理由": "第22名 | 116 (组三) | 总分62 | 和值=10 形态=10 跨度=8",
      "一句话说明": "和值8、跨度5，形态为组三，和值 形态 得分较高。",
      "评分明细": {
        "和值": [
          10,
          "和值=8"
        ],
        "跨度": [
          8,
          "跨度=5"
        ],
        "形态": [
          10,
          "形态=组三"
        ],
        "奇偶": [
          8,
          "奇=2"
        ],
        "大小": [
          8,
          "大=1"
        ],
        "012路": [
          3,
          "0路=1,1路=2,2路=0"
        ],
        "冷热": [
          8,
          "冷号=0"
        ],
        "遗漏": [
          7,
          "均遗=2.4"
        ],
        "多样性": [
          0,
          "组选唯一"
        ]
      }
    },
    {
      "排名": 23,
      "号码": "135",
      "group_number": "135",
      "和值": 9,
      "跨度": 4,
      "形态": "组六",
      "总分": 62,
      "推荐理由": "和值=11 跨度=10 形态=9",
      "展示理由": "第23名 | 135 (组六) | 总分62 | 和值=11 跨度=10 形态=9",
      "一句话说明": "和值9、跨度4，形态为组六，和值 跨度 得分较高。",
      "评分明细": {
        "和值": [
          11,
          "和值=9"
        ],
        "跨度": [
          10,
          "跨度=4"
        ],
        "形态": [
          9,
          "形态=组六"
        ],
        "奇偶": [
          2,
          "奇=3"
        ],
        "大小": [
          8,
          "大=1"
        ],
        "012路": [
          7,
          "0路=1,1路=1,2路=1"
        ],
        "冷热": [
          8,
          "冷号=0"
        ],
        "遗漏": [
          7,
          "均遗=2.4"
        ],
        "多样性": [
          0,
          "组选唯一"
        ]
      }
    },
    {
      "排名": 24,
      "号码": "136",
      "group_number": "136",
      "和值": 10,
      "跨度": 5,
      "形态": "组六",
      "总分": 62,
      "推荐理由": "和值=11 形态=9 跨度=8",
      "展示理由": "第24名 | 136 (组六) | 总分62 | 和值=11 形态=9 跨度=8",
      "一句话说明": "和值10、跨度5，形态为组六，和值 形态 得分较高。",
      "评分明细": {
        "和值": [
          11,
          "和值=10"
        ],
        "跨度": [
          8,
          "跨度=5"
        ],
        "形态": [
          9,
          "形态=组六"
        ],
        "奇偶": [
          8,
          "奇=2"
        ],
        "大小": [
          8,
          "大=1"
        ],
        "012路": [
          3,
          "0路=2,1路=1,2路=0"
        ],
        "冷热": [
          8,
          "冷号=0"
        ],
        "遗漏": [
          7,
          "均遗=2.4"
        ],
        "多样性": [
          0,
          "组选唯一"
        ]
      }
    },
    {
      "排名": 25,
      "号码": "256",
      "group_number": "256",
      "和值": 13,
      "跨度": 4,
      "形态": "组六",
      "总分": 62,
      "推荐理由": "跨度=10 和值=9 形态=9",
      "展示理由": "第25名 | 256 (组六) | 总分62 | 跨度=10 和值=9 形态=9",
      "一句话说明": "和值13、跨度4，形态为组六，跨度 和值 得分较高。",
      "评分明细": {
        "和值": [
          9,
          "和值=13"
        ],
        "跨度": [
          10,
          "跨度=4"
        ],
        "形态": [
          9,
          "形态=组六"
        ],
        "奇偶": [
          8,
          "奇=1"
        ],
        "大小": [
          8,
          "大=2"
        ],
        "012路": [
          3,
          "0路=1,1路=0,2路=2"
        ],
        "冷热": [
          8,
          "冷号=0"
        ],
        "遗漏": [
          7,
          "均遗=2.4"
        ],
        "多样性": [
          0,
          "组选唯一"
        ]
      }
    },
    {
      "排名": 26,
      "号码": "259",
      "group_number": "259",
      "和值": 16,
      "跨度": 7,
      "形态": "组六",
      "总分": 62,
      "推荐理由": "和值=12 跨度=9 形态=9",
      "展示理由": "第26名 | 259 (组六) | 总分62 | 和值=12 跨度=9 形态=9",
      "一句话说明": "和值16、跨度7，形态为组六，和值 跨度 得分较高。",
      "评分明细": {
        "和值": [
          12,
          "和值=16"
        ],
        "跨度": [
          9,
          "跨度=7"
        ],
        "形态": [
          9,
          "形态=组六"
        ],
        "奇偶": [
          8,
          "奇=2"
        ],
        "大小": [
          8,
          "大=2"
        ],
        "012路": [
          3,
          "0路=1,1路=0,2路=2"
        ],
        "冷热": [
          8,
          "冷号=0"
        ],
        "遗漏": [
          5,
          "均遗=2.4"
        ],
        "多样性": [
          0,
          "组选唯一"
        ]
      }
    },
    {
      "排名": 27,
      "号码": "269",
      "group_number": "269",
      "和值": 17,
      "跨度": 7,
      "形态": "组六",
      "总分": 62,
      "推荐理由": "和值=12 跨度=9 形态=9",
      "展示理由": "第27名 | 269 (组六) | 总分62 | 和值=12 跨度=9 形态=9",
      "一句话说明": "和值17、跨度7，形态为组六，和值 跨度 得分较高。",
      "评分明细": {
        "和值": [
          12,
          "和值=17"
        ],
        "跨度": [
          9,
          "跨度=7"
        ],
        "形态": [
          9,
          "形态=组六"
        ],
        "奇偶": [
          8,
          "奇=1"
        ],
        "大小": [
          8,
          "大=2"
        ],
        "012路": [
          3,
          "0路=2,1路=0,2路=1"
        ],
        "冷热": [
          8,
          "冷号=0"
        ],
        "遗漏": [
          5,
          "均遗=2.4"
        ],
        "多样性": [
          0,
          "组选唯一"
        ]
      }
    },
    {
      "排名": 28,
      "号码": "367",
      "group_number": "367",
      "和值": 16,
      "跨度": 4,
      "形态": "组六",
      "总分": 62,
      "推荐理由": "和值=12 跨度=10 形态=9",
      "展示理由": "第28名 | 367 (组六) | 总分62 | 和值=12 跨度=10 形态=9",
      "一句话说明": "和值16、跨度4，形态为组六，和值 跨度 得分较高。",
      "评分明细": {
        "和值": [
          12,
          "和值=16"
        ],
        "跨度": [
          10,
          "跨度=4"
        ],
        "形态": [
          9,
          "形态=组六"
        ],
        "奇偶": [
          8,
          "奇=2"
        ],
        "大小": [
          8,
          "大=2"
        ],
        "012路": [
          3,
          "0路=2,1路=1,2路=0"
        ],
        "冷热": [
          8,
          "冷号=0"
        ],
        "遗漏": [
          4,
          "均遗=2.4"
        ],
        "多样性": [
          0,
          "组选唯一"
        ]
      }
    },
    {
      "排名": 29,
      "号码": "018",
      "group_number": "018",
      "和值": 9,
      "跨度": 8,
      "形态": "组六",
      "总分": 61,
      "推荐理由": "和值=11 形态=9 奇偶=8",
      "展示理由": "第29名 | 018 (组六) | 总分61 | 和值=11 形态=9 奇偶=8",
      "一句话说明": "和值9、跨度8，形态为组六，和值 形态 得分较高。",
      "评分明细": {
        "和值": [
          11,
          "和值=9"
        ],
        "跨度": [
          6,
          "跨度=8"
        ],
        "形态": [
          9,
          "形态=组六"
        ],
        "奇偶": [
          8,
          "奇=1"
        ],
        "大小": [
          8,
          "大=1"
        ],
        "012路": [
          7,
          "0路=1,1路=1,2路=1"
        ],
        "冷热": [
          3,
          "冷号=1"
        ],
        "遗漏": [
          4,
          "均遗=2.4"
        ],
        "多样性": [
          5,
          "跨度8加5"
        ]
      }
    },
    {
      "排名": 30,
      "号码": "158",
      "group_number": "158",
      "和值": 14,
      "跨度": 7,
      "形态": "组六",
      "总分": 61,
      "推荐理由": "和值=9 跨度=9 形态=9",
      "展示理由": "第30名 | 158 (组六) | 总分61 | 和值=9 跨度=9 形态=9",
      "一句话说明": "和值14、跨度7，形态为组六，和值 跨度 得分较高。",
      "评分明细": {
        "和值": [
          9,
          "和值=14"
        ],
        "跨度": [
          9,
          "跨度=7"
        ],
        "形态": [
          9,
          "形态=组六"
        ],
        "奇偶": [
          8,
          "奇=2"
        ],
        "大小": [
          8,
          "大=2"
        ],
        "012路": [
          3,
          "0路=0,1路=1,2路=2"
        ],
        "冷热": [
          8,
          "冷号=0"
        ],
        "遗漏": [
          7,
          "均遗=2.4"
        ],
        "多样性": [
          0,
          "组选唯一"
        ]
      }
    }
  ]
}